autocommit/__init__.py
autocommit/cli.py
autocomplete_commit-0.1.1.dist-info/licenses/LICENSE
autocomplete_commit-0.1.1.dist-info/METADATA
autocomplete_commit-0.1.1.dist-info/WHEEL
autocomplete_commit-0.1.1.dist-info/entry_points.txt
autocomplete_commit-0.1.1.dist-info/top_level.txt
autocomplete_commit-0.1.1.dist-info/RECORD
