Metadata-Version: 2.4
Name: autocomplete-commit
Version: 0.1.1
Summary: A human-friendly git autocommit message generator
Author-email: Samuel <olawoleolaniran@gmail.com>
License: MIT
Requires-Python: >=3.7
License-File: LICENSE
Dynamic: license-file
